nlp_text_cleaner/__init__.py
nlp_text_cleaner/nlp_text_cleaner.py
nlp_text_cleaner-1.0.11.dist-info/LICENSE
nlp_text_cleaner-1.0.11.dist-info/METADATA
nlp_text_cleaner-1.0.11.dist-info/WHEEL
nlp_text_cleaner-1.0.11.dist-info/top_level.txt
nlp_text_cleaner-1.0.11.dist-info/RECORD
