Metadata-Version: 2.1
Name: nlp-text-cleaner
Version: 1.0.11
Summary: Clean the text for NLP project
Author-email: Sarang Mete <sarang0909.bds@gmail.com>
License: MIT License
Project-URL: Homepage, https://github.com/sarang0909/nlp_text_cleaner
Keywords: nlp,text cleaning,natural-language-processing,text-cleaning,text-preprocessing
Classifier: Programming Language :: Python :: 3.7
Classifier: Programming Language :: Python :: 3.8
Classifier: Programming Language :: Python :: 3.9
Classifier: Programming Language :: Python :: 3.10
Classifier: License :: OSI Approved :: MIT License
License-File: LICENSE
Requires-Dist: langdetect
Requires-Dist: nltk
Requires-Dist: regex
Requires-Dist: autocorrect
Provides-Extra: dev
Requires-Dist: black ; extra == 'dev'
Requires-Dist: pylint ; extra == 'dev'
Requires-Dist: isort ; extra == 'dev'
Requires-Dist: pip-tools ; extra == 'dev'
Requires-Dist: pytest ; extra == 'dev'
Requires-Dist: pytest-cov ; extra == 'dev'
